{
    "projectId": "quicklyresumethis1708",
    "endpoint": "https://sgp.cloud.appwrite.io/v1",
    "projectName": "quicklyresumethis",
    "settings": {
        "services": {
            "account": true,
            "avatars": true,
            "databases": true,
            "locale": true,
            "health": true,
            "storage": true,
            "teams": true,
            "users": true,
            "sites": true,
            "functions": true,
            "graphql": true,
            "messaging": true
        },
        "auth": {
            "methods": {
                "jwt": true,
                "phone": true,
                "invites": true,
                "anonymous": true,
                "email-otp": true,
                "magic-url": true,
                "email-password": true
            },
            "security": {
                "duration": 31536000,
                "limit": 0,
                "sessionsLimit": 10,
                "passwordHistory": 0,
                "passwordDictionary": false,
                "personalDataCheck": false,
                "sessionAlerts": false,
                "mockNumbers": []
            }
        }
    },
    "tablesDB": [
        {
            "$id": "69567ed80006c750c988",
            "name": "resumes-db",
            "enabled": true
        }
    ],
    "tables": [
        {
            "$id": "resume",
            "$permissions": [
                "create(\"users\")",
                "read(\"users\")",
                "update(\"users\")",
                "delete(\"users\")"
            ],
            "databaseId": "69567ed80006c750c988",
            "name": "resume",
            "enabled": true,
            "rowSecurity": false,
            "columns": [
                {
                    "key": "userId",
                    "type": "string",
                    "required": true,
                    "array": false,
                    "size": 36,
                    "default": null,
                    "encrypt": false
                },
                {
                    "key": "title",
                    "type": "string",
                    "required": true,
                    "array": false,
                    "size": 255,
                    "default": null,
                    "encrypt": false
                },
                {
                    "key": "content",
                    "type": "string",
                    "required": true,
                    "array": false,
                    "size": 1000,
                    "default": null,
                    "encrypt": false
                },
                {
                    "key": "status",
                    "type": "string",
                    "required": true,
                    "array": false,
                    "elements": [
                        "draft",
                        "submitted",
                        "approved",
                        "rejected",
                        "archived"
                    ],
                    "format": "enum",
                    "default": null
                },
                {
                    "key": "visibility",
                    "type": "string",
                    "required": true,
                    "array": false,
                    "elements": [
                        "public",
                        "private",
                        "restricted"
                    ],
                    "format": "enum",
                    "default": null
                },
                {
                    "key": "createdDate",
                    "type": "datetime",
                    "required": true,
                    "array": false,
                    "format": "",
                    "default": null
                },
                {
                    "key": "lastUpdated",
                    "type": "datetime",
                    "required": false,
                    "array": false,
                    "format": "",
                    "default": "1970-01-01T00:00:00Z"
                }
            ],
            "indexes": []
        }
    ],
    "buckets": [
        {
            "$id": "69568215003c390954e2",
            "$permissions": [
                "create(\"users\")",
                "read(\"users\")",
                "update(\"users\")",
                "delete(\"users\")"
            ],
            "fileSecurity": false,
            "name": "resumes-files",
            "enabled": true,
            "maximumFileSize": 5000000000,
            "allowedFileExtensions": [],
            "compression": "none",
            "encryption": true,
            "antivirus": true
        }
    ],
    "functions": [
        {
            "$id": "parse-resume",
            "execute": [],
            "name": "parse-resume",
            "enabled": true,
            "logging": true,
            "runtime": "node-22",
            "scopes": [],
            "events": [],
            "schedule": "",
            "timeout": 15,
            "entrypoint": "src/main.js",
            "commands": "",
            "specification": "s-0.5vcpu-512mb",
            "path": "functions/parse-resume"
        },
        {
            "$id": "695694c80023fe557361",
            "execute": [
                "any"
            ],
            "name": "enhance-text",
            "enabled": true,
            "logging": true,
            "runtime": "node-22",
            "scopes": [
                "users.read"
            ],
            "events": [],
            "schedule": "",
            "timeout": 15,
            "entrypoint": "src/main.js",
            "commands": "npm install",
            "specification": "s-0.5vcpu-512mb",
            "path": "functions/enhance-text"
        },
        {
            "$id": "695695b60034e3f38bbc",
            "execute": [
                "any"
            ],
            "name": "create-payment",
            "enabled": true,
            "logging": true,
            "runtime": "node-22",
            "scopes": [
                "users.read"
            ],
            "events": [],
            "schedule": "",
            "timeout": 15,
            "entrypoint": "src/main.js",
            "commands": "npm install",
            "specification": "s-0.5vcpu-512mb",
            "path": "functions/create-payment"
        },
        {
            "$id": "6956963f0016970e6b25",
            "execute": [
                "any"
            ],
            "name": "stripe-webhook",
            "enabled": true,
            "logging": true,
            "runtime": "node-22",
            "scopes": [
                "users.read"
            ],
            "events": [],
            "schedule": "",
            "timeout": 15,
            "entrypoint": "src/main.js",
            "commands": "npm install",
            "specification": "s-0.5vcpu-512mb",
            "path": "functions/stripe-webhook"
        },
        {
            "$id": "695697d9000c257c5032",
            "name": "s",
            "runtime": "node-22",
            "specification": "s-0.5vcpu-512mb",
            "execute": [
                "any"
            ],
            "events": [],
            "scopes": [
                "users.read"
            ],
            "schedule": "",
            "timeout": 15,
            "enabled": true,
            "logging": true,
            "entrypoint": "src/main.js",
            "commands": "npm install",
            "path": "functions/s"
        }
    ]
}